README.txt
setup.py
setup_recipe/__init__.py
setup_recipe.egg-info/PKG-INFO
setup_recipe.egg-info/SOURCES.txt
setup_recipe.egg-info/dependency_links.txt
setup_recipe.egg-info/entry_points.txt
setup_recipe.egg-info/top_level.txt
setup_recipe.egg-info/zip-safe