Metadata-Version: 1.1
Name: setup-recipe
Version: 1.0.alpha2
Summary: Buildout recipe, that runs the setup.py in all specified directories using custom interpreter, e.g. the one generated by zc.buildout.egg recipe.
Home-page: https://bitbucket.org/mdvorak/setup-recipe
Author: Michal Dvorak
Author-email: mikee@mdvorak.org
License: UNKNOWN
Platform: UNKNOWN
Classifier: Development Status :: 3 - Alpha
Classifier: Intended Audience :: Developers
Classifier: Operating System :: OS Independent
Classifier: Programming Language :: Python
Classifier: Programming Language :: Python :: 2.7
